bssapi/__init__.py
bssapi/__main__.py
bssapi/api/router/__init__.py
bssapi/api/router/parser/__init__.py
bssapi/api/router/parser/dbf.py
bssapi/core/dbf/__init__.py
bssapi/core/json/__init__.py
bssapi/schemas/exch.py
bssapi/schemas/http/headers/__init__.py
bssapi-0.1.3.dist-info/entry_points.txt
bssapi-0.1.3.dist-info/WHEEL
bssapi-0.1.3.dist-info/METADATA
bssapi-0.1.3.dist-info/RECORD
