Metadata-Version: 2.1
Name: bssapi
Version: 0.1.3
Summary: Функционал перефирийного взаимодействия корпоративной учетной системы BSS
Author: Anton Rastyazhenko
Author-email: rastyazhenko.anton@gmail.com
Requires-Python: >=3.8,<4.0
Classifier: Programming Language :: Python :: 3
Classifier: Programming Language :: Python :: 3.8
Requires-Dist: aioftp (>=0.18.0,<0.19.0)
Requires-Dist: attr (>=0.3.1,<0.4.0)
Requires-Dist: bssapi-dbfread (>=0.1.0,<0.2.0)
Requires-Dist: bssapi-schemas (>=0.1.7,<0.2.0)
Requires-Dist: fastapi[all] (>=0.61.1,<0.62.0)
Requires-Dist: lz4 (>=3.1.0,<4.0.0)
Requires-Dist: orjson (>=3.3.1,<4.0.0)
Requires-Dist: pydantic (>=1.6.1,<2.0.0)
Requires-Dist: pytest-asyncio (>=0.14.0,<0.15.0)
Requires-Dist: python-multipart (>=0.0.5,<0.0.6)
Requires-Dist: std-hash (>=0.1.0,<0.2.0)
